opyv8/__init__.py
opyv8/model.py
opyv8/predictor.py
opyv8/utils.py
onnx_predict_yolov8-1.0.6.dist-info/LICENSE
onnx_predict_yolov8-1.0.6.dist-info/METADATA
onnx_predict_yolov8-1.0.6.dist-info/WHEEL
onnx_predict_yolov8-1.0.6.dist-info/top_level.txt
onnx_predict_yolov8-1.0.6.dist-info/RECORD
