Metadata-Version: 2.1
Name: onnx-predict-yolov8
Version: 1.0.6
Author-email: Kasper Fromm Pedersen <kasperf@cs.aau.dk>, Kristian Torp <torp@cs.aau.dk>
Maintainer-email: Kasper Fromm Pedersen <kasperf@cs.aau.dk>
License: MIT License
Project-URL: homepage, https://www.cs.aau.dk/
Project-URL: repository, https://github.com/fromm1990/onnx-predict-yolov8
Keywords: ONNX,YOLOv8,onnxruntime,vision
Requires-Python: <3.12,>=3.8
License-File: LICENSE
Requires-Dist: numpy (>=1.20)
Requires-Dist: Pillow (>=9.1.0)
